[
  {
    "id": "awakening_void",
    "title": "The Null-Point Awakening",
    "content": "[INNER_MONOLOGUE] 'Where... am I? My head feels like it was hit by a freight train.' You open your eyes to a sky the color of a fresh bruise. You are lying in a glass-edged crater. The air is still, but you can feel a rhythmic pulsing deep in your bones. A flickering, gaseous light—a spirit fragment—hovers inches from your face. It is wounded, bleeding raw energy that smells like burnt copper and ozone. As your Earth-born logic tries to process the impossible, you feel a strange pull. The spirit isn't just near you; it's reacting to you. You are an anchor in this shifting reality.",
    "priority": 100,
    "prerequisites": {
      "location": "static_crater"
    },
    "choices": [
      {
        "id": "awakening_merge_thermal",
        "text": "Reach out and stabilize the spirit's heat. (Thermal Entropy Affinity)",
        "effects": {
          "experienceGain": 50,
          "setBlessedAbility": "thermal_entropy",
          "setGlobalFlags": { "blessed_skill_awakened": true, "affinity": "thermal" },
          "revealKnowledge": ["spirit_merging"]
        }
      },
      {
        "id": "awakening_merge_vector",
        "text": "Anchor the spirit's erratic movement. (Vector Resonance Affinity)",
        "effects": {
          "experienceGain": 50,
          "setBlessedAbility": "vector_resonance",
          "setGlobalFlags": { "blessed_skill_awakened": true, "affinity": "vector" },
          "revealKnowledge": ["spirit_merging"]
        }
      },
      {
        "id": "awakening_merge_biomorphic",
        "text": "Offer your own life-force to heal the flicker. (Biomorphic Flux Affinity)",
        "effects": {
          "experienceGain": 50,
          "setBlessedAbility": "biomorphic_flux",
          "setGlobalFlags": { "blessed_skill_awakened": true, "affinity": "biomorphic" },
          "revealKnowledge": ["spirit_merging"]
        }
      },
      {
        "id": "awakening_merge_cognitive",
        "text": "Merge your mind with the spirit's sensory echo. (Cognitive Distortion Affinity)",
        "effects": {
          "experienceGain": 50,
          "setBlessedAbility": "cognitive_distortion",
          "setGlobalFlags": { "blessed_skill_awakened": true, "affinity": "cognitive" },
          "revealKnowledge": ["spirit_merging"]
        }
      }
    ]
  },
  {
    "id": "crater_wake",
    "title": "The Scavenger's Shadow",
    "content": "The spirit merges into your chest with a silent, blinding flash. For a moment, you are the only thing that makes sense in this desert. [INNER_MONOLOGUE] 'What was that? I feel... grounded. Different.' A figure—{npc:kaelen}—is peering over the edge of the crater now, their hand drifting toward a rusted iron knife. As they take in your {player.height}, {player.bodyType} frame and the strange, steady light now radiating from your chest, they [NPC_REACT]. 'I don't know what void you leaked out of,' the figure calls down, 'but you've sucked the life right out of the air. If you want a ride out of here, you're going to have to prove you aren't just a walking curse.'",
    "priority": 90,
    "timeLimit": 15,
    "defaultChoiceId": "crater_wake_void",
    "prerequisites": {
      "location": "static_crater",
      "knowledgeFlags": ["spirit_merging"]
    },
    "choices": [
      {
        "id": "crater_wake_resonance",
        "text": "'Who are you? And where am I?'",
        "effects": {
          "alignmentChange": 5,
          "moveToLocation": "borderlands_outpost",
          "setGlobalFlags": { "met_kaelen": true, "kaelen_path": "resonance" },
          "revealNames": ["kaelen"],
          "experienceGain": 25
        }
      },
      {
        "id": "crater_wake_distortion",
        "text": "'Stay back. I'm not a curse, but I can be one if you touch that knife.'",
        "effects": {
          "purityChange": -5,
          "moveToLocation": "borderlands_outpost",
          "setGlobalFlags": { "met_kaelen": true, "kaelen_path": "distortion" },
          "experienceGain": 25
        }
      },
      {
        "id": "crater_wake_void",
        "text": "(Ignore them and climb out of the crater yourself).",
        "effects": {
          "moveToLocation": "borderlands_outpost",
          "setGlobalFlags": { "met_kaelen": false, "kaelen_path": "void" },
          "experienceGain": 10
        }
      }
    ]
  },
  {
    "id": "outpost_arrival_kaelen",
    "title": "Arriving with {npc:kaelen}",
    "content": "The scavenger leads you through a gap in the outpost's reinforced perimeter. The guards nod as you pass, their eyes lingering on {npc:kaelen}'s knife rather than your strange arrival. {npc:kaelen} spits into the red dust. 'The Market is ahead. Find a merchant named Vane if you want to trade that light in your chest for something useful. Just don't get caught by the Syndicate patrols.'",
    "priority": 50,
    "prerequisites": {
      "location": "borderlands_outpost",
      "lastChoiceId": "crater_wake_resonance"
    },
    "choices": [
      {
        "id": "outpost_hub_enter",
        "text": "Enter the Market Hub.",
        "effects": {
          "moveToLocation": "outpost_market",
          "experienceGain": 10
        }
      }
    ]
  },
  {
    "id": "outpost_arrival_distortion",
    "title": "Shadow of the Curse",
    "content": "{npc:kaelen} keeps a wary distance as you approach the outpost. 'You've got a sharp tongue and a strange light, stranger,' they mutter, 'but the Syndicate doesn't like loose ends. I'll get you inside, but after that, you're on your own.'",
    "priority": 50,
    "prerequisites": {
      "location": "borderlands_outpost",
      "lastChoiceId": "crater_wake_distortion"
    },
    "choices": [
      {
        "id": "outpost_hub_enter_dist",
        "text": "Enter the Market Hub.",
        "effects": {
          "moveToLocation": "outpost_market",
          "experienceGain": 10
        }
      }
    ]
  },
  {
    "id": "outpost_arrival_alone",
    "title": "The Lonely Outpost",
    "content": "You arrive at the Borderlands Outpost alone, your feet heavy with red dust. Without a local to vouch for you, the iron gates feel more like a cage than a sanctuary. A Syndicate guard blocks your path, their rifle humming with thermal energy. 'No strangers without a permit. Unless you've got Shards or something to trade.'",
    "priority": 50,
    "prerequisites": {
      "location": "borderlands_outpost",
      "lastChoiceId": "crater_wake_void"
    },
    "choices": [
      {
        "id": "outpost_bribe_guard",
        "text": "Bribe the guard (50 Shards).",
        "effects": {
          "wealthChange": -50,
          "moveToLocation": "outpost_market",
          "experienceGain": 10
        }
      },
      {
        "id": "outpost_sneak_market",
        "text": "[Finesse 12] Sneak past through the ventilation ducts.",
        "effects": {
          "moveToLocation": "outpost_market",
          "experienceGain": 20
        }
      }
    ]
  },
  {
    "id": "market_hub_main",
    "title": "The Market Hub",
    "content": "The Outpost Market is a frantic web of commerce and desperation. Steam vents hiss, and the smell of ozone is constant. [INNER_MONOLOGUE] 'This is where the world actually happens.' Merchants hawk fragments of technology, and scavengers recount tales of the deeper wastes. You are free to act here, but every action takes time.",
    "priority": 10,
    "repeatable": true,
    "prerequisites": {
      "location": "outpost_market"
    },
    "choices": [
      {
        "id": "hub_action_scavenge",
        "text": "[SCAVENGE] Look for usable scrap in the outskirts.",
        "effects": {
          "setGlobalFlags": { "hub_action": "scavenge" }
        }
      },
      {
        "id": "hub_action_socialize",
        "text": "[SOCIALIZE] Listen to the rumors in the tavern.",
        "effects": {
          "setGlobalFlags": { "hub_action": "socialize" }
        }
      },
      {
        "id": "hub_action_work",
        "text": "[WORK] Check the Syndicate's bounty board.",
        "effects": {
          "setGlobalFlags": { "hub_action": "work" }
        }
      }
    ]
  },
  {
    "id": "event_enforcer_harassment",
    "title": "Syndicate Compliance Check",
    "content": "A {npc:syndicate_enforcer_grunt} blocks your path, their iron baton sparking with static energy. They look at the light pulsing in your chest with visible disgust. 'Newcomer, isn't it? You're leaking unregistered resonance. That's a Tier 1 infraction. Pay the 50 Shard Static-Levy now, or come with us to the Watch-Side Surplus for processing.'",
    "priority": 25,
    "prerequisites": {
      "location": "outpost_market",
      "npc_loc_syndicate_enforcer_grunt": "outpost_market"
    },
    "choices": [
      {
        "id": "enforcer_pay_levy",
        "text": "Pay the levy (50 Shards).",
        "effects": {
          "wealthChange": -50,
          "experienceGain": 5
        }
      },
      {
        "id": "enforcer_persuade",
        "text": "[Logic 12] Explain that your 'static' is actually a byproduct of a new energy-saving blueprint.",
        "effects": {
          "experienceGain": 20,
          "setGlobalFlags": { "enforcer_fooled": true }
        }
      },
      {
        "id": "enforcer_fight",
        "text": "Refuse and draw your weapon.",
        "effects": {
          "setGlobalFlags": { "combat_started": true, "target_npc": "syndicate_enforcer_grunt" }
        }
      }
    ]
  },
  {
    "id": "event_socialize_tavern",
    "title": "The Rusty Gear Tavern",
    "content": "You push through the heavy leather flaps of the local tavern. It smells of stale beer and burning sage. In the corner, a merchant is hawking curative salves. At the bar, a drunken engineer is rambling about the inefficiency of the local steam engines. [INNER_MONOLOGUE] 'I could probably fix that engine if I showed them the Rankine cycle.'",
    "priority": 20,
    "repeatable": true,
    "prerequisites": {
      "location": "outpost_market",
      "globalFlags": { "hub_action": "socialize" }
    },
    "choices": [
      {
        "id": "tavern_buy_salve",
        "text": "Buy an Epidermal Salve (20 Shards).",
        "effects": {
          "wealthChange": -20,
          "addItem": ["epidermal_salve"],
          "setGlobalFlags": { "hub_action": "none" }
        }
      },
      {
        "id": "tavern_buy_bloodroot",
        "text": "Buy Bloodroot Herb (15 Shards).",
        "effects": {
          "wealthChange": -15,
          "addItem": ["bloodroot"],
          "setGlobalFlags": { "hub_action": "none" }
        }
      },
      {
        "id": "tavern_share_blueprint",
        "text": "[Logic 12] Explain the Rankine Cycle to the engineer.",
        "effects": {
          "experienceGain": 40,
          "alignmentChange": 5,
          "setGlobalFlags": { "hub_action": "none" },
          "revealKnowledge": ["steam_cycle"]
        }
      },
      {
        "id": "tavern_chat_kaelen",
        "text": "Talk to {npc:kaelen} at the bar.",
        "effects": {
          "setGlobalFlags": { "hub_action": "chat_kaelen" }
        }
      },
      {
        "id": "tavern_leave",
        "text": "Have a drink and leave.",
        "effects": {
          "wealthChange": -5,
          "experienceGain": 5,
          "setGlobalFlags": { "hub_action": "none" }
        }
      }
    ]
  },
  {
    "id": "story_kaelen_warning",
    "title": "A Gravelly Warning",
    "content": "{npc:kaelen} looks up from their murky drink. 'You're making too much noise, {player.name}. The static you're dragging behind you is like a flare in the void. Captain Vane has already sent a search party for the source. If you don't find a way to mask that resonance, you'll meet Thorne sooner than you'd like.'",
    "priority": 30,
    "prerequisites": {
      "globalFlags": { "hub_action": "chat_kaelen", "npc_loc_kaelen": "borderlands_warrens" }
    },
    "choices": [
      {
        "id": "kaelen_ask_vane",
        "text": "'Who is Captain Vane?'",
        "effects": {
          "setGlobalFlags": { "hub_action": "none", "story_progress": "knows_vane" },
          "revealKnowledge": ["syndicate_hierarchy"]
        }
      }
    ]
  },
  {
    "id": "story_vane_summon",
    "title": "The Captain's Summons",
    "content": "Two Syndicate Enforcers corner you outside the market. 'Captain Vane requests your presence at the Iron Watch HQ. He doesn't like it when anomalies wander his territory without an audit. Don't make this difficult.'",
    "priority": 80,
    "prerequisites": {
      "location": "outpost_market",
      "requiredMilestone": "reached_outpost",
      "globalFlags": { "story_progress": "knows_vane" },
      "minWealth": 300
    },
    "choices": [
      {
        "id": "vane_accept",
        "text": "Follow them to the HQ.",
        "effects": {
          "moveToLocation": "iron_watch_hq",
          "setGlobalFlags": { "story_progress": "vane_meeting" }
        }
      },
      {
        "id": "vane_refuse",
        "text": "Run for the Warrens.",
        "effects": {
          "moveToLocation": "borderlands_warrens",
          "setGlobalFlags": { "story_progress": "vane_evaded" },
          "experienceGain": 10
        }
      }
    ]
    },
    {
    "id": "journey_crater_to_outpost",
    "title": "The Glass Desert",
    "content": "The walk to the outpost is a test of endurance. The red dust clogs your lungs, and the rhythmic pulsing of the world is deafening in the silence. [INNER_MONOLOGUE] 'If this is the world now, I need to adapt fast.' You pass the skeletal remains of a steam-crawler, its brass gears partially fused by entropy. You can feel the residue of a massive energy discharge here.",
    "priority": 60,
    "prerequisites": {
      "location": "dust_flats"
    },
    "choices": [
      {
        "id": "journey_scavenge_wreck",
        "text": "[SCAVENGE] Search the crawler for parts.",
        "effects": {
          "wealthChange": 25,
          "experienceGain": 15,
          "moveToLocation": "borderlands_outpost"
        }
      },
      {
        "id": "journey_push_on",
        "text": "Keep moving. The outpost is in sight.",
        "effects": {
          "moveToLocation": "borderlands_outpost",
          "experienceGain": 5,
          "revealKnowledge": ["reached_outpost"]
        }
      }
    ]
    },
    {
    "id": "outcome_hub_scavenge",
    "title": "Scavenging Results",
    "content": "You spend hours combing the outskirts of the market. The ground is littered with 'Ghost-Static'—the psychic residue of forgotten memories. You manage to find: {game.lastLoot}. [INNER_MONOLOGUE] 'It's not much, but it's a start.'",
    "priority": 25,
    "prerequisites": {
      "location": "outpost_market",
      "globalFlags": { "hub_action": "scavenge" }
    },
    "choices": [
      {
        "id": "scavenge_success",
        "text": "Return to the Market Hub.",
        "effects": {
          "triggerLoot": "low_wastes",
          "experienceGain": 10,
          "setGlobalFlags": { "hub_action": "none" }
        }
      }
      ]
      },
      {
      "id": "discover_blessed_skill",
      "title": "A Resonance Realized",
      "content": "You focus on the {player.blessedSkill}. As you apply your understanding of systemic resonance, the 'warmth' in your marrow suddenly crystallizes into a name and a function. [INNER_MONOLOGUE] 'It's not just heat. It's a signature. I can... stabilize the air around me.'",
      "priority": 95,
      "prerequisites": {
      "knowledgeFlags": ["spirit_merging"],
      "requiredStats": { "sync": 15 },
      "globalFlags": { "skill_discovery_imminent": true }
      },
      "choices": [
      {
        "id": "skill_awakened",
        "text": "Embrace the Echo-Anchor.",
        "effects": {
          "revealBlessedSkill": true,
          "experienceGain": 50,
          "setGlobalFlags": { "skill_discovery_imminent": false }
        }
      }
      ]
      }
      ]